DragAndDropTk/__init__.py
DragAndDropTk/drag_and_drop_tk.py
draganddroptk-0.1.3.dist-info/METADATA
draganddroptk-0.1.3.dist-info/WHEEL
draganddroptk-0.1.3.dist-info/licenses/LICENSE
draganddroptk-0.1.3.dist-info/RECORD
