Metadata-Version: 2.1
Name: DragAndDropTk
Version: 0.1.1
Summary: A generic drag and drop widget to Tkinter applications
Author-email: Lucas Rocha <lucash.rocha@hotmail.com>
License: MIT License
Classifier: Programming Language :: Python :: 3
Classifier: License :: OSI Approved :: MIT License
Classifier: Operating System :: OS Independent
Requires-Python: >=3.10
License-File: LICENSE
